pylsp_pyre/__init__.py
pylsp_pyre/plugin.py
python_lsp_pyre-0.1.3.dist-info/METADATA
python_lsp_pyre-0.1.3.dist-info/WHEEL
python_lsp_pyre-0.1.3.dist-info/entry_points.txt
python_lsp_pyre-0.1.3.dist-info/RECORD
