Metadata-Version: 2.1
Name: python-lsp-pyre
Version: 0.1.3
Summary: Pyre linting plugin for pylsp
License: MIT
Author: Duncan Hill
Author-email: python.projects@cricalix.net
Requires-Python: >=3.9,<4.0
Classifier: License :: OSI Approved :: MIT License
Classifier: Programming Language :: Python :: 3
Classifier: Programming Language :: Python :: 3.9
Classifier: Programming Language :: Python :: 3.10
Classifier: Programming Language :: Python :: 3.11
Requires-Dist: pyre-check (>=0.9.18,<0.10.0)
Requires-Dist: python-lsp-server (>=1.7.3,<2.0.0)
